<?xml version="1.0" encoding="utf-8"?>
<QuizList>
    <Quiz QuizIndex="0" QuizType="CuJu">
        <QuizContent>
            蹴鞠最早记载于哪本书？
        </QuizContent>
        <Options>
            <Option IsAnswer="False">
                西京杂记
            </Option>
            <Option IsAnswer="False">
                刘向别录
            </Option>
            <Option IsAnswer="True">
                史记
            </Option>
            <Option IsAnswer="False">
                蹴鞠新书
            </Option>
        </Options>
    </Quiz>
    <Quiz QuizIndex="1" QuizType="CuJu">
        <QuizContent>
            蹴鞠最早起源于何地？
        </QuizContent>
        <Options>
            <Option IsAnswer="True">
                齐国临淄
            </Option>
            <Option IsAnswer="False">
                西晋洛阳
            </Option>
            <Option IsAnswer="False">
                北齐邺城
            </Option>
            <Option IsAnswer="False">
                宋代建康
            </Option>
        </Options>
    </Quiz>
    <Quiz QuizIndex="2" QuizType="BingXi">
        <QuizContent>
            清代冰嬉大典不包含下列哪项体育项目？
        </QuizContent>
        <Options>
            <Option IsAnswer="False">
                抢等
            </Option>
            <Option IsAnswer="False">
                抢球
            </Option>
            <Option IsAnswer="False">
                转龙射球
            </Option>
            <Option IsAnswer="True">
                冰壶
            </Option>
        </Options>
    </Quiz>
    <Quiz QuizIndex="3" QuizType="BingXi">
        <QuizContent>
            哪个朝代冰嬉发展最为鼎盛？
        </QuizContent>
        <Options>
            <Option IsAnswer="False">
                唐代
            </Option>
            <Option IsAnswer="True">
                清代
            </Option>
            <Option IsAnswer="False">
                元代
            </Option>
            <Option IsAnswer="False">
                明代
            </Option>
        </Options>
    </Quiz>
    <Quiz QuizIndex="4" QuizType="ChuiWan">
        <QuizContent>
            捶丸由哪项运动演变而来？
        </QuizContent>
        <Options>
            <Option IsAnswer="True">
                布打球
            </Option>
            <Option IsAnswer="False">
                蹴鞠
            </Option>
            <Option IsAnswer="False">
                马球
            </Option>
            <Option IsAnswer="False">
                击壤
            </Option>
        </Options>
    </Quiz>
    <Quiz QuizIndex="5" QuizType="ChuiWan">
        <QuizContent>
            捶丸的竞赛规则较高尔夫的竞赛规则早出现了多少年？
        </QuizContent>
        <Options>
            <Option IsAnswer="False">
                564年
            </Option>
            <Option IsAnswer="False">
                346年
            </Option>
            <Option IsAnswer="True">
                472年
            </Option>
            <Option IsAnswer="False">
                258年
            </Option>
        </Options>
    </Quiz>
    <Quiz QuizIndex="6" QuizType="MaQiu">
        <QuizContent>
            曹植《名都篇》中“连骑击鞠壤，巧捷惟万端”的诗句是描写哪项体育项目的？
        </QuizContent>
        <Options>
            <Option IsAnswer="False">
                蹴鞠
            </Option>
            <Option IsAnswer="False">
                投壶
            </Option>
            <Option IsAnswer="False">
                相扑
            </Option>
            <Option IsAnswer="True">
                马球
            </Option>
        </Options>
    </Quiz>
    <Quiz QuizIndex="7" QuizType="MaQiu">
        <QuizContent>
            马球起源于哪个朝代？
        </QuizContent>
        <Options>
            <Option IsAnswer="False">
                唐代
            </Option>
            <Option IsAnswer="False">
                元代
            </Option>
            <Option IsAnswer="True">
                汉代
            </Option>
            <Option IsAnswer="False">
                明代
            </Option>
        </Options>
    </Quiz>
    <Quiz QuizIndex="8" QuizType="WuQinXi">
        <QuizContent>
            五禽戏是下面哪位名医所创？
        </QuizContent>
        <Options>
            <Option IsAnswer="False">
                扁鹊
            </Option>
            <Option IsAnswer="True">
                华佗
            </Option>
            <Option IsAnswer="False">
                张仲景
            </Option>
            <Option IsAnswer="False">
                李时珍
            </Option>
        </Options>
    </Quiz>
    <Quiz QuizIndex="9" QuizType="WuQinXi">
        <QuizContent>
            五禽戏中不包括下列那种动物?
        </QuizContent>
        <Options>
            <Option IsAnswer="False">
                虎
            </Option>
            <Option IsAnswer="False">
                熊
            </Option>
            <Option IsAnswer="True">
                鸡
            </Option>
            <Option IsAnswer="False">
                鹤
            </Option>
        </Options>
    </Quiz>
</QuizList>